MANIFEST.in
README.md
setup.py
msdsl/__init__.py
msdsl/assignment.py
msdsl/circuit.py
msdsl/files.py
msdsl/function.py
msdsl/lfsr.py
msdsl/model.py
msdsl/msdsl.sv
msdsl/rf.py
msdsl/util.py
msdsl.egg-info/PKG-INFO
msdsl.egg-info/SOURCES.txt
msdsl.egg-info/dependency_links.txt
msdsl.egg-info/not-zip-safe
msdsl.egg-info/requires.txt
msdsl.egg-info/top_level.txt
msdsl/eqn/__init__.py
msdsl/eqn/cases.py
msdsl/eqn/deriv.py
msdsl/eqn/eqn_list.py
msdsl/eqn/eqn_sys.py
msdsl/eqn/lds.py
msdsl/expr/__init__.py
msdsl/expr/analyze.py
msdsl/expr/compression.py
msdsl/expr/expr.py
msdsl/expr/extras.py
msdsl/expr/format.py
msdsl/expr/signals.py
msdsl/expr/simplify.py
msdsl/expr/svreal.py
msdsl/expr/table.py
msdsl/generator/__init__.py
msdsl/generator/case_statement.py
msdsl/generator/generator.py
msdsl/generator/svreal.py
msdsl/generator/tree_op.py
msdsl/generator/verilog.py
msdsl/plugin/__init__.py
msdsl/plugin/msdsl.py
msdsl/templates/__init__.py
msdsl/templates/channel.py
msdsl/templates/lds.py
msdsl/templates/oscillator.py
msdsl/templates/saturation.py
msdsl/templates/uniform.py
tests/__init__.py
tests/common.py
tests/adc/__init__.py
tests/adc/test_adc.py
tests/arb_noise/__init__.py
tests/arb_noise/test_arb_noise.py
tests/binding/__init__.py
tests/binding/test_binding.py
tests/chan_interp/__init__.py
tests/chan_interp/test_chan_interp.py
tests/circuit_ind_sw/__init__.py
tests/circuit_ind_sw/test_circuit_ind_sw.py
tests/circuit_rc/__init__.py
tests/circuit_rc/test_circuit_rc.py
tests/circuit_sw/__init__.py
tests/circuit_sw/test_circuit_sw.py
tests/comparator/__init__.py
tests/comparator/test_comparator.py
tests/ctle_interp/__init__.py
tests/ctle_interp/test_ctle_interp.py
tests/ctle_interp2/__init__.py
tests/ctle_interp2/test_ctle_interp2.py
tests/dac/__init__.py
tests/dac/test_dac.py
tests/det/__init__.py
tests/det/test_det.py
tests/eqn_no_dyn/__init__.py
tests/eqn_no_dyn/test_eqn_no_dyn.py
tests/func_sim/__init__.py
tests/func_sim/test_func_sim.py
tests/gauss_inv_cdf/__init__.py
tests/gauss_inv_cdf/test_gauss_inv_cdf.py
tests/gaussian_noise/__init__.py
tests/gaussian_noise/test_gaussian_noise.py
tests/lfsr_sim/__init__.py
