Metadata-Version: 2.1
Name: msdsl
Version: 0.3.7
Summary: Library for generating synthesizable mixed-signal models for FPGA emulation
Home-page: https://github.com/sgherbst/msdsl
Author: Steven Herbst
Author-email: sgherbst@gmail.com
License: MIT
Download-URL: https://github.com/sgherbst/msdsl/archive/v0.3.7.tar.gz
Keywords: analog,mixed-signal,mixed signal,behavioral,real number model,real number models,rnm,rnms,model,models,generator,verilog,system-verilog,system verilog,synthesizable,emulation,fpga
Platform: UNKNOWN
Classifier: Development Status :: 3 - Alpha
Classifier: Intended Audience :: Developers
Classifier: Topic :: Scientific/Engineering :: Electronic Design Automation (EDA)
Classifier: License :: OSI Approved :: MIT License
Classifier: Programming Language :: Python :: 3.7
Requires-Python: >=3.7
